unittest_parallel/__init__.py
unittest_parallel/__main__.py
unittest_parallel/main.py
unittest_parallel-1.7.5.dist-info/licenses/LICENSE
unittest_parallel-1.7.5.dist-info/METADATA
unittest_parallel-1.7.5.dist-info/WHEEL
unittest_parallel-1.7.5.dist-info/entry_points.txt
unittest_parallel-1.7.5.dist-info/top_level.txt
unittest_parallel-1.7.5.dist-info/RECORD
