Metadata-Version: 2.4
Name: unittest-parallel
Version: 1.7.5
Summary: Parallel unit test runner with coverage support
Home-page: https://github.com/craigahobbs/unittest-parallel
Author: Craig A. Hobbs
Author-email: craigahobbs@gmail.com
License: MIT
Keywords: test,unittest,coverage,parallel
Classifier: Development Status :: 5 - Production/Stable
Classifier: Intended Audience :: Developers
Classifier: Operating System :: OS Independent
Classifier: Programming Language :: Python :: 3.9
Classifier: Programming Language :: Python :: 3.10
Classifier: Programming Language :: Python :: 3.11
Classifier: Programming Language :: Python :: 3.12
Classifier: Programming Language :: Python :: 3.13
Classifier: Programming Language :: Python :: 3.14
Classifier: Topic :: Software Development :: Testing
Classifier: Topic :: Utilities
License-File: LICENSE
Requires-Dist: coverage>=5.1
Dynamic: license-file
